Workbook

Sheet 30-Day Calendar
A1: 30-DAY CONTENT CALENDAR · 24 Aug – 22 Sep 2026 · Urban Auto Hub
A2: Full detail in urban-auto-hub/CALENDAR-30D.md. Tick Shot / Hook B / Posted as you go. EVERY Reel needs two hooks and a cover frame. Log results in the Post Log tab at +24h. Prices, unit counts and names are placeholders — fill from real documents on the day.
A3: Day | B3: Date | C3: Category | D3: Format | E3: Frame-1 text | F3: Hook (spoken) | G3: Key message | H3: CTA | I3: Metric | J3: Hook style | K3: Shot? | L3: Hook B? | M3: Posted?
A4: D01 | B4: 46258 | C4: Authority | D4: Reel 60-75s | E4: KERTAS DULU, KERETA KEMUDIAN | F4: Semua orang tunjuk kereta. Takda orang tunjuk kertas ni. | G4: Every car starts as a Japanese auction sheet - grade, mileage, panel damage map, inspector notes. If a seller can't produce it, that's the question to ask. | H4: Nak kami tarik auction sheet untuk unit yang korang pertimbang? Comment 'SHEET'. | I4: Saves | J4: Everything on the table
A5: D02 | B5: 46259 | C5: Educational | D5: Carousel 6 cards - PINNED | E5: GRED 4.5 vs GRED 4 | F5: Beza satu titik. Beza harga RM___. | G5: Decode Japanese auction grades 5 / 4.5 / 4 / 3.5 / R / RA - one card each, plain Malay, what each means for the person paying. | H5: Save ni sebelum korang tengok kereta. Comment gred yang korang tak faham. | I5: Saves | J5: Price shock
A6: D03 | B6: 46260 | C6: Entertaining | D6: Reel 30-45s | E6: TAKDA KAT MALAYSIA | F6: (cold engine start, no music) Kereta ni takda kat sini. Bukan sebab mahal. | G6: Dealers buy what sells fast, so unusual specs never get ordered locally. They exist at auction every week. | H6: Kereta apa korang cari yang takda kat Malaysia? Comment. | I6: 3-sec rate | J6: Cold sound
A7: D04 | B7: 46261 | C7: Personal | D7: Reel 45-60s | E7: 2:00 PAGI | F7: Pukul 2 pagi kat KK. Auction Jepun start pukul 3. | G7: What bidding actually looks like - the time zone, the live board, one shot, losing a car by 10,000 yen while your customer sleeps. | H7: Follow kalau nak tengok kami bid live minggu depan. | I7: Follows | J7: Mid-action start
A8: D05 | B8: 46262 | C8: Community | D8: Still split-screen + long caption | E8: A ATAU B? | F8: Satu huruf ja. A atau B? | G8: Same model, two auction specs. Both gettable. Which would you actually take? | H8: Comment A atau B. Yang menang, kami cari unit dia minggu depan. | I8: COMMENTS | J8: Split screen
A9: D06 | B9: 46263 | C9: Authority | D9: FB Live 15-20 min | E9: (live) | F9: Live: kami buka auction sheet untuk 3 unit yang korang minta. | G9: Read real sheets out loud on camera - grade, panel map, inspector notes, mileage record. Answer questions live. | H9: Comment model - kami tarik sheet dia sekarang. | I9: Comments + watch | J9: Direct challenge
A10: D07 | B10: 46264 | C10: Community | D10: Carousel + poll | E10: 3 UNIT SAMPAI MINGGU NI | F10: Tiga unit sampai. Satu tu spec yang customer minta empat bulan lepas. | G10: What landed this week + one spec search that finally closed. Proof for buyers, quiet proof for watching dealers. | H10: Poll: unit apa korang nak kami cari bulan depan? | I10: Shares | J10: Receipts
A11: D08 | B11: 46265 | C11: Educational | D11: Reel 60-75s | E11: RM___ -> RM___ | F11: RM___ kat Jepun. RM___ sampai driveway korang. Duit tu pergi mana? | G11: The full cost stack, every line named: auction price, inland transport, shipping, marine insurance, duty, excise, SST, permit, registration, margin. | H11: Save ni. Comment 'KOS' kalau nak breakdown untuk model korang. | I11: Saves | J11: Price shock
A12: D09 | B12: 46266 | C12: Authority | D12: Carousel - PINNED | E12: (price + warranty burned in, static) | F12: Stock minggu ni - dan empat spec yang kami tengah cari untuk customer. | G12: Available units PLUS open spec searches. The searches are what prove the sourcing service is real and busy. | H12: Comment nombor unit, atau WhatsApp spec korang. | I12: Convos | J12: Receipts
A13: D10 | B13: 46267 | C13: Entertaining | D13: Reel 30-45s | E13: 11 WARNA. MALAYSIA: 2. | F13: Kami boleh mintak sebelas warna. Malaysia ada dua. | G13: Local stock is chosen by resale speed so the palette collapses to white and black. Auction has the full range. This is the whole argument for sourcing to spec. | H13: Warna apa korang mau tapi takda kat sini? Comment. | I13: 3-sec rate | J13: Bold claim
A14: D11 | B14: 46268 | C14: Educational | D14: Reel 60-75s | E14: TAHUN 3 = TITIK MANIS | F14: Recond tiga tahun atau baru? Ini nombornya. | G14: 3-5 year cars are the largest slice of the Malaysian used market: steepest depreciation absorbed, modern safety tech still there. Run the maths on one named model. | H14: Save. Comment model korang, kami kira. | I14: Saves | J14: Result-first
A15: D12 | B15: 46269 | C15: Community | D15: Reel 30s | E15: TEKA HARGA | F15: Teka harga unit ni. Yang paling dekat, kami belanja detailing. | G15: A guessing game on a real available unit. Guessing is free and fun - which is why it beats 'what do you think?' | H15: Comment satu nombor. Jawapan esok. | I15: COMMENTS | J15: Unanswered question
... A33: D30 | B33: 46287 | C33: Educational | D33: Carousel 7 cards - NEW PINNED | E33: AUCTION JEPUN -> DRIVEWAY KORANG | F33: Berapa lama sebenarnya? Ini timeline penuh. | G33: The complete journey week by week: auction day, winning bid, inland transport, vessel, port, customs, permit, registration, inspection, handover. Most-asked DM question, answered once, pinned forever. EVERGREEN. | H33: Save. WhatsApp bila korang dah sedia mula. | I33: Saves | J33: Result-first tutorial
A35: THE MIX — and why it isn't even
A36: Authority | B36: 7 | C36: The sourcing machine is the differentiator. Documents and results are the moat.
A37: Educational | B37: 7 | C37: Drives SAVES - the mechanism that keeps you present across a 60-day research window.
A38: Community | B38: 7 | C38: Comments are your weakest number (4/month). Seven deliberate attempts to fix it.
A39: Entertaining | B39: 5 | C39: Top-of-funnel reach. Enough to feed the algorithm, not enough to attract the wrong audience.
A40: Personal | B40: 4 | C40: Deliberately scarcest. You cannot schedule 8 genuine stories - a manufactured one is worse than none.
A41: TOTAL | B41: 30

Sheet Post Log
A1: POST LOG — one row per post, filled +24h after publishing
A2: YELLOW = you type it. GREY = calculated, don't touch. The +24h read is the ritual: log it, then write the Verdict — what the FIRST THREE SECONDS did, and why. Verdict/Action are auto-suggested from the 3-sec rate; override in Notes if you disagree.
A3: Date | B3: Day | C3: Format | D3: Pillar | E3: Hook style | F3: Hook ver (A/B) | G3: Car / subject | H3: Dealer partner | I3: Views | J3: 3-sec views | K3: 3-sec rate | L3: Avg watch (s) | M3: Runtime (s) | N3: Avg % viewed | O3: Saves | P3: Shares | Q3: Comments | R3: Follows | S3: Convos | T3: Verdict | U3: Action | V3: Notes
A4: 46259 | B4: =IF($A4="","",TEXT($A4,"ddd")) -> Tue | C4: Reel | D4: Feature x Sabah | E4: Price shock | F4: A | G4: Vellfire 2.5 ZG | H4: [dealer name] | I4: 1240 | J4: 236 | K4: =IF(OR($I4="",$J4=""),"",IFERROR($J4/$I4,"")) -> 0.19032258 | L4: 14 | M4: 58 | N4: =IF(OR($L4="",$M4=""),"",IFERROR($L4/$M4,"")) -> 0.24137931 | O4: 9 | P4: 4 | Q4: 7 | R4: 3 | S4: 1 | T4: =IF($K4="","",IF($K4>=0.25,"WIN",IF($K4>=0.2,"OK","FAIL"))) -> FAIL | U4: =IF($K4="","",IF($K4<0.2,"REPOST WITH HOOK B",IF($K4>=0.25,"Bank hook in PLAYBOOK","Hold - watch next run"))) -> REPOST WITH HOOK B | V4: EXAMPLE ROW - delete before use. Hook B was the cold-start sound version.
B5: =IF($A5="","",TEXT($A5,"ddd")) | K5: =IF(OR($I5="",$J5=""),"",IFERROR($J5/$I5,"")) | N5: =IF(OR($L5="",$M5=""),"",IFERROR($L5/$M5,"")) | T5: =IF($K5="","",IF($K5>=0.25,"WIN",IF($K5>=0.2,"OK","FAIL"))) | U5: =IF($K5="","",IF($K5<0.2,"REPOST WITH HOOK B",IF($K5>=0.25,"Bank hook in PLAYBOOK","Hold - watch next run")))
B6: =IF($A6="","",TEXT($A6,"ddd")) | K6: =IF(OR($I6="",$J6=""),"",IFERROR($J6/$I6,"")) | N6: =IF(OR($L6="",$M6=""),"",IFERROR($L6/$M6,"")) | T6: =IF($K6="","",IF($K6>=0.25,"WIN",IF($K6>=0.2,"OK","FAIL"))) | U6: =IF($K6="","",IF($K6<0.2,"REPOST WITH HOOK B",IF($K6>=0.25,"Bank hook in PLAYBOOK","Hold - watch next run")))
B7: =IF($A7="","",TEXT($A7,"ddd")) | K7: =IF(OR($I7="",$J7=""),"",IFERROR($J7/$I7,"")) | N7: =IF(OR($L7="",$M7=""),"",IFERROR($L7/$M7,"")) | T7: =IF($K7="","",IF($K7>=0.25,"WIN",IF($K7>=0.2,"OK","FAIL"))) | U7: =IF($K7="","",IF($K7<0.2,"REPOST WITH HOOK B",IF($K7>=0.25,"Bank hook in PLAYBOOK","Hold - watch next run")))
B8: =IF($A8="","",TEXT($A8,"ddd")) | K8: =IF(OR($I8="",$J8=""),"",IFERROR($J8/$I8,"")) | N8: =IF(OR($L8="",$M8=""),"",IFERROR($L8/$M8,"")) | T8: =IF($K8="","",IF($K8>=0.25,"WIN",IF($K8>=0.2,"OK","FAIL"))) | U8: =IF($K8="","",IF($K8<0.2,"REPOST WITH HOOK B",IF($K8>=0.25,"Bank hook in PLAYBOOK","Hold - watch next run")))
B9: =IF($A9="","",TEXT($A9,"ddd")) | K9: =IF(OR($I9="",$J9=""),"",IFERROR($J9/$I9,"")) | N9: =IF(OR($L9="",$M9=""),"",IFERROR($L9/$M9,"")) | T9: =IF($K9="","",IF($K9>=0.25,"WIN",IF($K9>=0.2,"OK","FAIL"))) | U9: =IF($K9="","",IF($K9<0.2,"REPOST WITH HOOK B",IF($K9>=0.25,"Bank hook in PLAYBOOK","Hold - watch next run")))
B10: =IF($A10="","",TEXT($A10,"ddd")) | K10: =IF(OR($I10="",$J10=""),"",IFERROR($J10/$I10,"")) | N10: =IF(OR($L10="",$M10=""),"",IFERROR($L10/$M10,"")) | T10: =IF($K10="","",IF($K10>=0.25,"WIN",IF($K10>=0.2,"OK","FAIL"))) | U10: =IF($K10="","",IF($K10<0.2,"REPOST WITH HOOK B",IF($K10>=0.25,"Bank hook in PLAYBOOK","Hold - watch next run")))
B11: =IF($A11="","",TEXT($A11,"ddd")) | K11: =IF(OR($I11="",$J11=""),"",IFERROR($J11/$I11,"")) | N11: =IF(OR($L11="",$M11=""),"",IFERROR($L11/$M11,"")) | T11: =IF($K11="","",IF($K11>=0.25,"WIN",IF($K11>=0.2,"OK","FAIL"))) | U11: =IF($K11="","",IF($K11<0.2,"REPOST WITH HOOK B",IF($K11>=0.25,"Bank hook in PLAYBOOK","Hold - watch next run")))
B12: =IF($A12="","",TEXT($A12,"ddd")) | K12: =IF(OR($I12="",$J12=""),"",IFERROR($J12/$I12,"")) | N12: =IF(OR($L12="",$M12=""),"",IFERROR($L12/$M12,"")) | T12: =IF($K12="","",IF($K12>=0.25,"WIN",IF($K12>=0.2,"OK","FAIL"))) | U12: =IF($K12="","",IF($K12<0.2,"REPOST WITH HOOK B",IF($K12>=0.25,"Bank hook in PLAYBOOK","Hold - watch next run")))
B13: =IF($A13="","",TEXT($A13,"ddd")) | K13: =IF(OR($I13="",$J13=""),"",IFERROR($J13/$I13,"")) | N13: =IF(OR($L13="",$M13=""),"",IFERROR($L13/$M13,"")) | T13: =IF($K13="","",IF($K13>=0.25,"WIN",IF($K13>=0.2,"OK","FAIL"))) | U13: =IF($K13="","",IF($K13<0.2,"REPOST WITH HOOK B",IF($K13>=0.25,"Bank hook in PLAYBOOK","Hold - watch next run")))
B14: =IF($A14="","",TEXT($A14,"ddd")) | K14: =IF(OR($I14="",$J14=""),"",IFERROR($J14/$I14,"")) | N14: =IF(OR($L14="",$M14=""),"",IFERROR($L14/$M14,"")) | T14: =IF($K14="","",IF($K14>=0.25,"WIN",IF($K14>=0.2,"OK","FAIL"))) | U14: =IF($K14="","",IF($K14<0.2,"REPOST WITH HOOK B",IF($K14>=0.25,"Bank hook in PLAYBOOK","Hold - watch next run")))
B15: =IF($A15="","",TEXT($A15,"ddd")) | K15: =IF(OR($I15="",$J15=""),"",IFERROR($J15/$I15,"")) | N15: =IF(OR($L15="",$M15=""),"",IFERROR($L15/$M15,"")) | T15: =IF($K15="","",IF($K15>=0.25,"WIN",IF($K15>=0.2,"OK","FAIL"))) | U15: =IF($K15="","",IF($K15<0.2,"REPOST WITH HOOK B",IF($K15>=0.25,"Bank hook in PLAYBOOK","Hold - watch next run")))
B16: =IF($A16="","",TEXT($A16,"ddd")) | K16: =IF(OR($I16="",$J16=""),"",IFERROR($J16/$I16,"")) | N16: =IF(OR($L16="",$M16=""),"",IFERROR($L16/$M16,"")) | T16: =IF($K16="","",IF($K16>=0.25,"WIN",IF($K16>=0.2,"OK","FAIL"))) | U16: =IF($K16="","",IF($K16<0.2,"REPOST WITH HOOK B",IF($K16>=0.25,"Bank hook in PLAYBOOK","Hold - watch next run")))
... B203: =IF($A203="","",TEXT($A203,"ddd")) | K203: =IF(OR($I203="",$J203=""),"",IFERROR($J203/$I203,"")) | N203: =IF(OR($L203="",$M203=""),"",IFERROR($L203/$M203,"")) | T203: =IF($K203="","",IF($K203>=0.25,"WIN",IF($K203>=0.2,"OK","FAIL"))) | U203: =IF($K203="","",IF($K203<0.2,"REPOST WITH HOOK B",IF($K203>=0.25,"Bank hook in PLAYBOOK","Hold - watch next run")))

Sheet Weekly
A1: WEEKLY ROLL-UP — fill 'Week start' (Monday), everything else calculates
A2: Sunday 4pm ritual, before running WEEKLY-TASK.md. Only the yellow cells are typed: the Monday date, outbound comments made, and active dealer partners. Targets follow the 90-day ladder in GROWTH-SYSTEM.md PART 3.
A3: Week start (Mon) | B3: Posts | C3: Views | D3: 3-sec rate | E3: Avg % viewed | F3: Saves+Shares | G3: Comments | H3: Net follows | I3: Convos | J3: Outbound comments | K3: Dealer partners | L3: North star vs target
A4: 46258 | B4: =IF($A4="","",COUNTIFS('Post Log'!$A$4:$A$203,">="&$A4,'Post Log'!$A$4:$A$203,"<"&$A4+7)) -> 1 | C4: =IF($A4="","",SUMIFS('Post Log'!$I$4:$I$203,'Post Log'!$A$4:$A$203,">="&$A4,'Post Log'!$A$4:$A$203,"<"&$A4+7)) -> 1240 | D4: =IF(OR($A4="",SUMIFS('Post Log'!$I$4:$I$203,'Post Log'!$A$4:$A$203,">="&$A4,'Post Log'!$A$4:$A$203,"<"&$A4+7)=0),"",SUMIFS('Post Log'!$J$4:$J$203,'Post Log'!$A$4:$A$203,">="&$A4,'Post Log'!$A$4:$A$203,"<"&$A4+7)/SUMIFS('Post Log'!$I$4:$I$203,'Post Log'!$A$4:$A$203,">="&$A4,'Post Log'!$A$4:$A$203,"<"&$A4+7)) -> 0.19032258 | E4: =IF(OR($A4="",SUMIFS('Post Log'!$M$4:$M$203,'Post Log'!$A$4:$A$203,">="&$A4,'Post Log'!$A$4:$A$203,"<"&$A4+7)=0),"",SUMIFS('Post Log'!$L$4:$L$203,'Post Log'!$A$4:$A$203,">="&$A4,'Post Log'!$A$4:$A$203,"<"&$A4+7)/SUMIFS('Post Log'!$M$4:$M$203,'Post Log'!$A$4:$A$203,">="&$A4,'Post Log'!$A$4:$A$203,"<"&$A4+7)) -> 0.24137931 | F4: =IF($A4="","",SUMIFS('Post Log'!$O$4:$O$203,'Post Log'!$A$4:$A$203,">="&$A4,'Post Log'!$A$4:$A$203,"<"&$A4+7)+SUMIFS('Post Log'!$P$4:$P$203,'Post Log'!$A$4:$A$203,">="&$A4,'Post Log'!$A$4:$A$203,"<"&$A4+7)) -> 13 | G4: =IF($A4="","",SUMIFS('Post Log'!$Q$4:$Q$203,'Post Log'!$A$4:$A$203,">="&$A4,'Post Log'!$A$4:$A$203,"<"&$A4+7)) -> 7 | H4: =IF($A4="","",SUMIFS('Post Log'!$R$4:$R$203,'Post Log'!$A$4:$A$203,">="&$A4,'Post Log'!$A$4:$A$203,"<"&$A4+7)) -> 3 | I4: =IF($A4="","",SUMIFS('Post Log'!$S$4:$S$203,'Post Log'!$A$4:$A$203,">="&$A4,'Post Log'!$A$4:$A$203,"<"&$A4+7)) -> 1 | J4: 75 | K4: 2 | L4: =IF($D4="","",IF($D4>=Targets!$B$4,"ON TARGET",TEXT(Targets!$B$4-$D4,"0.0%")&" to go")) -> 1.0% to go
B5: =IF($A5="","",COUNTIFS('Post Log'!$A$4:$A$203,">="&$A5,'Post Log'!$A$4:$A$203,"<"&$A5+7)) | C5: =IF($A5="","",SUMIFS('Post Log'!$I$4:$I$203,'Post Log'!$A$4:$A$203,">="&$A5,'Post Log'!$A$4:$A$203,"<"&$A5+7)) | D5: =IF(OR($A5="",SUMIFS('Post Log'!$I$4:$I$203,'Post Log'!$A$4:$A$203,">="&$A5,'Post Log'!$A$4:$A$203,"<"&$A5+7)=0),"",SUMIFS('Post Log'!$J$4:$J$203,'Post Log'!$A$4:$A$203,">="&$A5,'Post Log'!$A$4:$A$203,"<"&$A5+7)/SUMIFS('Post Log'!$I$4:$I$203,'Post Log'!$A$4:$A$203,">="&$A5,'Post Log'!$A$4:$A$203,"<"&$A5+7)) | E5: =IF(OR($A5="",SUMIFS('Post Log'!$M$4:$M$203,'Post Log'!$A$4:$A$203,">="&$A5,'Post Log'!$A$4:$A$203,"<"&$A5+7)=0),"",SUMIFS('Post Log'!$L$4:$L$203,'Post Log'!$A$4:$A$203,">="&$A5,'Post Log'!$A$4:$A$203,"<"&$A5+7)/SUMIFS('Post Log'!$M$4:$M$203,'Post Log'!$A$4:$A$203,">="&$A5,'Post Log'!$A$4:$A$203,"<"&$A5+7)) | F5: =IF($A5="","",SUMIFS('Post Log'!$O$4:$O$203,'Post Log'!$A$4:$A$203,">="&$A5,'Post Log'!$A$4:$A$203,"<"&$A5+7)+SUMIFS('Post Log'!$P$4:$P$203,'Post Log'!$A$4:$A$203,">="&$A5,'Post Log'!$A$4:$A$203,"<"&$A5+7)) | G5: =IF($A5="","",SUMIFS('Post Log'!$Q$4:$Q$203,'Post Log'!$A$4:$A$203,">="&$A5,'Post Log'!$A$4:$A$203,"<"&$A5+7)) | H5: =IF($A5="","",SUMIFS('Post Log'!$R$4:$R$203,'Post Log'!$A$4:$A$203,">="&$A5,'Post Log'!$A$4:$A$203,"<"&$A5+7)) | I5: =IF($A5="","",SUMIFS('Post Log'!$S$4:$S$203,'Post Log'!$A$4:$A$203,">="&$A5,'Post Log'!$A$4:$A$203,"<"&$A5+7)) | L5: =IF($D5="","",IF($D5>=Targets!$B$4,"ON TARGET",TEXT(Targets!$B$4-$D5,"0.0%")&" to go"))
B6: =IF($A6="","",COUNTIFS('Post Log'!$A$4:$A$203,">="&$A6,'Post Log'!$A$4:$A$203,"<"&$A6+7)) | C6: =IF($A6="","",SUMIFS('Post Log'!$I$4:$I$203,'Post Log'!$A$4:$A$203,">="&$A6,'Post Log'!$A$4:$A$203,"<"&$A6+7)) | D6: =IF(OR($A6="",SUMIFS('Post Log'!$I$4:$I$203,'Post Log'!$A$4:$A$203,">="&$A6,'Post Log'!$A$4:$A$203,"<"&$A6+7)=0),"",SUMIFS('Post Log'!$J$4:$J$203,'Post Log'!$A$4:$A$203,">="&$A6,'Post Log'!$A$4:$A$203,"<"&$A6+7)/SUMIFS('Post Log'!$I$4:$I$203,'Post Log'!$A$4:$A$203,">="&$A6,'Post Log'!$A$4:$A$203,"<"&$A6+7)) | E6: =IF(OR($A6="",SUMIFS('Post Log'!$M$4:$M$203,'Post Log'!$A$4:$A$203,">="&$A6,'Post Log'!$A$4:$A$203,"<"&$A6+7)=0),"",SUMIFS('Post Log'!$L$4:$L$203,'Post Log'!$A$4:$A$203,">="&$A6,'Post Log'!$A$4:$A$203,"<"&$A6+7)/SUMIFS('Post Log'!$M$4:$M$203,'Post Log'!$A$4:$A$203,">="&$A6,'Post Log'!$A$4:$A$203,"<"&$A6+7)) | F6: =IF($A6="","",SUMIFS('Post Log'!$O$4:$O$203,'Post Log'!$A$4:$A$203,">="&$A6,'Post Log'!$A$4:$A$203,"<"&$A6+7)+SUMIFS('Post Log'!$P$4:$P$203,'Post Log'!$A$4:$A$203,">="&$A6,'Post Log'!$A$4:$A$203,"<"&$A6+7)) | G6: =IF($A6="","",SUMIFS('Post Log'!$Q$4:$Q$203,'Post Log'!$A$4:$A$203,">="&$A6,'Post Log'!$A$4:$A$203,"<"&$A6+7)) | H6: =IF($A6="","",SUMIFS('Post Log'!$R$4:$R$203,'Post Log'!$A$4:$A$203,">="&$A6,'Post Log'!$A$4:$A$203,"<"&$A6+7)) | I6: =IF($A6="","",SUMIFS('Post Log'!$S$4:$S$203,'Post Log'!$A$4:$A$203,">="&$A6,'Post Log'!$A$4:$A$203,"<"&$A6+7)) | L6: =IF($D6="","",IF($D6>=Targets!$B$4,"ON TARGET",TEXT(Targets!$B$4-$D6,"0.0%")&" to go"))
B7: =IF($A7="","",COUNTIFS('Post Log'!$A$4:$A$203,">="&$A7,'Post Log'!$A$4:$A$203,"<"&$A7+7)) | C7: =IF($A7="","",SUMIFS('Post Log'!$I$4:$I$203,'Post Log'!$A$4:$A$203,">="&$A7,'Post Log'!$A$4:$A$203,"<"&$A7+7)) | D7: =IF(OR($A7="",SUMIFS('Post Log'!$I$4:$I$203,'Post Log'!$A$4:$A$203,">="&$A7,'Post Log'!$A$4:$A$203,"<"&$A7+7)=0),"",SUMIFS('Post Log'!$J$4:$J$203,'Post Log'!$A$4:$A$203,">="&$A7,'Post Log'!$A$4:$A$203,"<"&$A7+7)/SUMIFS('Post Log'!$I$4:$I$203,'Post Log'!$A$4:$A$203,">="&$A7,'Post Log'!$A$4:$A$203,"<"&$A7+7)) | E7: =IF(OR($A7="",SUMIFS('Post Log'!$M$4:$M$203,'Post Log'!$A$4:$A$203,">="&$A7,'Post Log'!$A$4:$A$203,"<"&$A7+7)=0),"",SUMIFS('Post Log'!$L$4:$L$203,'Post Log'!$A$4:$A$203,">="&$A7,'Post Log'!$A$4:$A$203,"<"&$A7+7)/SUMIFS('Post Log'!$M$4:$M$203,'Post Log'!$A$4:$A$203,">="&$A7,'Post Log'!$A$4:$A$203,"<"&$A7+7)) | F7: =IF($A7="","",SUMIFS('Post Log'!$O$4:$O$203,'Post Log'!$A$4:$A$203,">="&$A7,'Post Log'!$A$4:$A$203,"<"&$A7+7)+SUMIFS('Post Log'!$P$4:$P$203,'Post Log'!$A$4:$A$203,">="&$A7,'Post Log'!$A$4:$A$203,"<"&$A7+7)) | G7: =IF($A7="","",SUMIFS('Post Log'!$Q$4:$Q$203,'Post Log'!$A$4:$A$203,">="&$A7,'Post Log'!$A$4:$A$203,"<"&$A7+7)) | H7: =IF($A7="","",SUMIFS('Post Log'!$R$4:$R$203,'Post Log'!$A$4:$A$203,">="&$A7,'Post Log'!$A$4:$A$203,"<"&$A7+7)) | I7: =IF($A7="","",SUMIFS('Post Log'!$S$4:$S$203,'Post Log'!$A$4:$A$203,">="&$A7,'Post Log'!$A$4:$A$203,"<"&$A7+7)) | L7: =IF($D7="","",IF($D7>=Targets!$B$4,"ON TARGET",TEXT(Targets!$B$4-$D7,"0.0%")&" to go"))
B8: =IF($A8="","",COUNTIFS('Post Log'!$A$4:$A$203,">="&$A8,'Post Log'!$A$4:$A$203,"<"&$A8+7)) | C8: =IF($A8="","",SUMIFS('Post Log'!$I$4:$I$203,'Post Log'!$A$4:$A$203,">="&$A8,'Post Log'!$A$4:$A$203,"<"&$A8+7)) | D8: =IF(OR($A8="",SUMIFS('Post Log'!$I$4:$I$203,'Post Log'!$A$4:$A$203,">="&$A8,'Post Log'!$A$4:$A$203,"<"&$A8+7)=0),"",SUMIFS('Post Log'!$J$4:$J$203,'Post Log'!$A$4:$A$203,">="&$A8,'Post Log'!$A$4:$A$203,"<"&$A8+7)/SUMIFS('Post Log'!$I$4:$I$203,'Post Log'!$A$4:$A$203,">="&$A8,'Post Log'!$A$4:$A$203,"<"&$A8+7)) | E8: =IF(OR($A8="",SUMIFS('Post Log'!$M$4:$M$203,'Post Log'!$A$4:$A$203,">="&$A8,'Post Log'!$A$4:$A$203,"<"&$A8+7)=0),"",SUMIFS('Post Log'!$L$4:$L$203,'Post Log'!$A$4:$A$203,">="&$A8,'Post Log'!$A$4:$A$203,"<"&$A8+7)/SUMIFS('Post Log'!$M$4:$M$203,'Post Log'!$A$4:$A$203,">="&$A8,'Post Log'!$A$4:$A$203,"<"&$A8+7)) | F8: =IF($A8="","",SUMIFS('Post Log'!$O$4:$O$203,'Post Log'!$A$4:$A$203,">="&$A8,'Post Log'!$A$4:$A$203,"<"&$A8+7)+SUMIFS('Post Log'!$P$4:$P$203,'Post Log'!$A$4:$A$203,">="&$A8,'Post Log'!$A$4:$A$203,"<"&$A8+7)) | G8: =IF($A8="","",SUMIFS('Post Log'!$Q$4:$Q$203,'Post Log'!$A$4:$A$203,">="&$A8,'Post Log'!$A$4:$A$203,"<"&$A8+7)) | H8: =IF($A8="","",SUMIFS('Post Log'!$R$4:$R$203,'Post Log'!$A$4:$A$203,">="&$A8,'Post Log'!$A$4:$A$203,"<"&$A8+7)) | I8: =IF($A8="","",SUMIFS('Post Log'!$S$4:$S$203,'Post Log'!$A$4:$A$203,">="&$A8,'Post Log'!$A$4:$A$203,"<"&$A8+7)) | L8: =IF($D8="","",IF($D8>=Targets!$B$4,"ON TARGET",TEXT(Targets!$B$4-$D8,"0.0%")&" to go"))
B9: =IF($A9="","",COUNTIFS('Post Log'!$A$4:$A$203,">="&$A9,'Post Log'!$A$4:$A$203,"<"&$A9+7)) | C9: =IF($A9="","",SUMIFS('Post Log'!$I$4:$I$203,'Post Log'!$A$4:$A$203,">="&$A9,'Post Log'!$A$4:$A$203,"<"&$A9+7)) | D9: =IF(OR($A9="",SUMIFS('Post Log'!$I$4:$I$203,'Post Log'!$A$4:$A$203,">="&$A9,'Post Log'!$A$4:$A$203,"<"&$A9+7)=0),"",SUMIFS('Post Log'!$J$4:$J$203,'Post Log'!$A$4:$A$203,">="&$A9,'Post Log'!$A$4:$A$203,"<"&$A9+7)/SUMIFS('Post Log'!$I$4:$I$203,'Post Log'!$A$4:$A$203,">="&$A9,'Post Log'!$A$4:$A$203,"<"&$A9+7)) | E9: =IF(OR($A9="",SUMIFS('Post Log'!$M$4:$M$203,'Post Log'!$A$4:$A$203,">="&$A9,'Post Log'!$A$4:$A$203,"<"&$A9+7)=0),"",SUMIFS('Post Log'!$L$4:$L$203,'Post Log'!$A$4:$A$203,">="&$A9,'Post Log'!$A$4:$A$203,"<"&$A9+7)/SUMIFS('Post Log'!$M$4:$M$203,'Post Log'!$A$4:$A$203,">="&$A9,'Post Log'!$A$4:$A$203,"<"&$A9+7)) | F9: =IF($A9="","",SUMIFS('Post Log'!$O$4:$O$203,'Post Log'!$A$4:$A$203,">="&$A9,'Post Log'!$A$4:$A$203,"<"&$A9+7)+SUMIFS('Post Log'!$P$4:$P$203,'Post Log'!$A$4:$A$203,">="&$A9,'Post Log'!$A$4:$A$203,"<"&$A9+7)) | G9: =IF($A9="","",SUMIFS('Post Log'!$Q$4:$Q$203,'Post Log'!$A$4:$A$203,">="&$A9,'Post Log'!$A$4:$A$203,"<"&$A9+7)) | H9: =IF($A9="","",SUMIFS('Post Log'!$R$4:$R$203,'Post Log'!$A$4:$A$203,">="&$A9,'Post Log'!$A$4:$A$203,"<"&$A9+7)) | I9: =IF($A9="","",SUMIFS('Post Log'!$S$4:$S$203,'Post Log'!$A$4:$A$203,">="&$A9,'Post Log'!$A$4:$A$203,"<"&$A9+7)) | L9: =IF($D9="","",IF($D9>=Targets!$B$4,"ON TARGET",TEXT(Targets!$B$4-$D9,"0.0%")&" to go"))
B10: =IF($A10="","",COUNTIFS('Post Log'!$A$4:$A$203,">="&$A10,'Post Log'!$A$4:$A$203,"<"&$A10+7)) | C10: =IF($A10="","",SUMIFS('Post Log'!$I$4:$I$203,'Post Log'!$A$4:$A$203,">="&$A10,'Post Log'!$A$4:$A$203,"<"&$A10+7)) | D10: =IF(OR($A10="",SUMIFS('Post Log'!$I$4:$I$203,'Post Log'!$A$4:$A$203,">="&$A10,'Post Log'!$A$4:$A$203,"<"&$A10+7)=0),"",SUMIFS('Post Log'!$J$4:$J$203,'Post Log'!$A$4:$A$203,">="&$A10,'Post Log'!$A$4:$A$203,"<"&$A10+7)/SUMIFS('Post Log'!$I$4:$I$203,'Post Log'!$A$4:$A$203,">="&$A10,'Post Log'!$A$4:$A$203,"<"&$A10+7)) | E10: =IF(OR($A10="",SUMIFS('Post Log'!$M$4:$M$203,'Post Log'!$A$4:$A$203,">="&$A10,'Post Log'!$A$4:$A$203,"<"&$A10+7)=0),"",SUMIFS('Post Log'!$L$4:$L$203,'Post Log'!$A$4:$A$203,">="&$A10,'Post Log'!$A$4:$A$203,"<"&$A10+7)/SUMIFS('Post Log'!$M$4:$M$203,'Post Log'!$A$4:$A$203,">="&$A10,'Post Log'!$A$4:$A$203,"<"&$A10+7)) | F10: =IF($A10="","",SUMIFS('Post Log'!$O$4:$O$203,'Post Log'!$A$4:$A$203,">="&$A10,'Post Log'!$A$4:$A$203,"<"&$A10+7)+SUMIFS('Post Log'!$P$4:$P$203,'Post Log'!$A$4:$A$203,">="&$A10,'Post Log'!$A$4:$A$203,"<"&$A10+7)) | G10: =IF($A10="","",SUMIFS('Post Log'!$Q$4:$Q$203,'Post Log'!$A$4:$A$203,">="&$A10,'Post Log'!$A$4:$A$203,"<"&$A10+7)) | H10: =IF($A10="","",SUMIFS('Post Log'!$R$4:$R$203,'Post Log'!$A$4:$A$203,">="&$A10,'Post Log'!$A$4:$A$203,"<"&$A10+7)) | I10: =IF($A10="","",SUMIFS('Post Log'!$S$4:$S$203,'Post Log'!$A$4:$A$203,">="&$A10,'Post Log'!$A$4:$A$203,"<"&$A10+7)) | L10: =IF($D10="","",IF($D10>=Targets!$B$4,"ON TARGET",TEXT(Targets!$B$4-$D10,"0.0%")&" to go"))
B11: =IF($A11="","",COUNTIFS('Post Log'!$A$4:$A$203,">="&$A11,'Post Log'!$A$4:$A$203,"<"&$A11+7)) | C11: =IF($A11="","",SUMIFS('Post Log'!$I$4:$I$203,'Post Log'!$A$4:$A$203,">="&$A11,'Post Log'!$A$4:$A$203,"<"&$A11+7)) | D11: =IF(OR($A11="",SUMIFS('Post Log'!$I$4:$I$203,'Post Log'!$A$4:$A$203,">="&$A11,'Post Log'!$A$4:$A$203,"<"&$A11+7)=0),"",SUMIFS('Post Log'!$J$4:$J$203,'Post Log'!$A$4:$A$203,">="&$A11,'Post Log'!$A$4:$A$203,"<"&$A11+7)/SUMIFS('Post Log'!$I$4:$I$203,'Post Log'!$A$4:$A$203,">="&$A11,'Post Log'!$A$4:$A$203,"<"&$A11+7)) | E11: =IF(OR($A11="",SUMIFS('Post Log'!$M$4:$M$203,'Post Log'!$A$4:$A$203,">="&$A11,'Post Log'!$A$4:$A$203,"<"&$A11+7)=0),"",SUMIFS('Post Log'!$L$4:$L$203,'Post Log'!$A$4:$A$203,">="&$A11,'Post Log'!$A$4:$A$203,"<"&$A11+7)/SUMIFS('Post Log'!$M$4:$M$203,'Post Log'!$A$4:$A$203,">="&$A11,'Post Log'!$A$4:$A$203,"<"&$A11+7)) | F11: =IF($A11="","",SUMIFS('Post Log'!$O$4:$O$203,'Post Log'!$A$4:$A$203,">="&$A11,'Post Log'!$A$4:$A$203,"<"&$A11+7)+SUMIFS('Post Log'!$P$4:$P$203,'Post Log'!$A$4:$A$203,">="&$A11,'Post Log'!$A$4:$A$203,"<"&$A11+7)) | G11: =IF($A11="","",SUMIFS('Post Log'!$Q$4:$Q$203,'Post Log'!$A$4:$A$203,">="&$A11,'Post Log'!$A$4:$A$203,"<"&$A11+7)) | H11: =IF($A11="","",SUMIFS('Post Log'!$R$4:$R$203,'Post Log'!$A$4:$A$203,">="&$A11,'Post Log'!$A$4:$A$203,"<"&$A11+7)) | I11: =IF($A11="","",SUMIFS('Post Log'!$S$4:$S$203,'Post Log'!$A$4:$A$203,">="&$A11,'Post Log'!$A$4:$A$203,"<"&$A11+7)) | L11: =IF($D11="","",IF($D11>=Targets!$B$4,"ON TARGET",TEXT(Targets!$B$4-$D11,"0.0%")&" to go"))
B12: =IF($A12="","",COUNTIFS('Post Log'!$A$4:$A$203,">="&$A12,'Post Log'!$A$4:$A$203,"<"&$A12+7)) | C12: =IF($A12="","",SUMIFS('Post Log'!$I$4:$I$203,'Post Log'!$A$4:$A$203,">="&$A12,'Post Log'!$A$4:$A$203,"<"&$A12+7)) | D12: =IF(OR($A12="",SUMIFS('Post Log'!$I$4:$I$203,'Post Log'!$A$4:$A$203,">="&$A12,'Post Log'!$A$4:$A$203,"<"&$A12+7)=0),"",SUMIFS('Post Log'!$J$4:$J$203,'Post Log'!$A$4:$A$203,">="&$A12,'Post Log'!$A$4:$A$203,"<"&$A12+7)/SUMIFS('Post Log'!$I$4:$I$203,'Post Log'!$A$4:$A$203,">="&$A12,'Post Log'!$A$4:$A$203,"<"&$A12+7)) | E12: =IF(OR($A12="",SUMIFS('Post Log'!$M$4:$M$203,'Post Log'!$A$4:$A$203,">="&$A12,'Post Log'!$A$4:$A$203,"<"&$A12+7)=0),"",SUMIFS('Post Log'!$L$4:$L$203,'Post Log'!$A$4:$A$203,">="&$A12,'Post Log'!$A$4:$A$203,"<"&$A12+7)/SUMIFS('Post Log'!$M$4:$M$203,'Post Log'!$A$4:$A$203,">="&$A12,'Post Log'!$A$4:$A$203,"<"&$A12+7)) | F12: =IF($A12="","",SUMIFS('Post Log'!$O$4:$O$203,'Post Log'!$A$4:$A$203,">="&$A12,'Post Log'!$A$4:$A$203,"<"&$A12+7)+SUMIFS('Post Log'!$P$4:$P$203,'Post Log'!$A$4:$A$203,">="&$A12,'Post Log'!$A$4:$A$203,"<"&$A12+7)) | G12: =IF($A12="","",SUMIFS('Post Log'!$Q$4:$Q$203,'Post Log'!$A$4:$A$203,">="&$A12,'Post Log'!$A$4:$A$203,"<"&$A12+7)) | H12: =IF($A12="","",SUMIFS('Post Log'!$R$4:$R$203,'Post Log'!$A$4:$A$203,">="&$A12,'Post Log'!$A$4:$A$203,"<"&$A12+7)) | I12: =IF($A12="","",SUMIFS('Post Log'!$S$4:$S$203,'Post Log'!$A$4:$A$203,">="&$A12,'Post Log'!$A$4:$A$203,"<"&$A12+7)) | L12: =IF($D12="","",IF($D12>=Targets!$B$4,"ON TARGET",TEXT(Targets!$B$4-$D12,"0.0%")&" to go"))
B13: =IF($A13="","",COUNTIFS('Post Log'!$A$4:$A$203,">="&$A13,'Post Log'!$A$4:$A$203,"<"&$A13+7)) | C13: =IF($A13="","",SUMIFS('Post Log'!$I$4:$I$203,'Post Log'!$A$4:$A$203,">="&$A13,'Post Log'!$A$4:$A$203,"<"&$A13+7)) | D13: =IF(OR($A13="",SUMIFS('Post Log'!$I$4:$I$203,'Post Log'!$A$4:$A$203,">="&$A13,'Post Log'!$A$4:$A$203,"<"&$A13+7)=0),"",SUMIFS('Post Log'!$J$4:$J$203,'Post Log'!$A$4:$A$203,">="&$A13,'Post Log'!$A$4:$A$203,"<"&$A13+7)/SUMIFS('Post Log'!$I$4:$I$203,'Post Log'!$A$4:$A$203,">="&$A13,'Post Log'!$A$4:$A$203,"<"&$A13+7)) | E13: =IF(OR($A13="",SUMIFS('Post Log'!$M$4:$M$203,'Post Log'!$A$4:$A$203,">="&$A13,'Post Log'!$A$4:$A$203,"<"&$A13+7)=0),"",SUMIFS('Post Log'!$L$4:$L$203,'Post Log'!$A$4:$A$203,">="&$A13,'Post Log'!$A$4:$A$203,"<"&$A13+7)/SUMIFS('Post Log'!$M$4:$M$203,'Post Log'!$A$4:$A$203,">="&$A13,'Post Log'!$A$4:$A$203,"<"&$A13+7)) | F13: =IF($A13="","",SUMIFS('Post Log'!$O$4:$O$203,'Post Log'!$A$4:$A$203,">="&$A13,'Post Log'!$A$4:$A$203,"<"&$A13+7)+SUMIFS('Post Log'!$P$4:$P$203,'Post Log'!$A$4:$A$203,">="&$A13,'Post Log'!$A$4:$A$203,"<"&$A13+7)) | G13: =IF($A13="","",SUMIFS('Post Log'!$Q$4:$Q$203,'Post Log'!$A$4:$A$203,">="&$A13,'Post Log'!$A$4:$A$203,"<"&$A13+7)) | H13: =IF($A13="","",SUMIFS('Post Log'!$R$4:$R$203,'Post Log'!$A$4:$A$203,">="&$A13,'Post Log'!$A$4:$A$203,"<"&$A13+7)) | I13: =IF($A13="","",SUMIFS('Post Log'!$S$4:$S$203,'Post Log'!$A$4:$A$203,">="&$A13,'Post Log'!$A$4:$A$203,"<"&$A13+7)) | L13: =IF($D13="","",IF($D13>=Targets!$B$4,"ON TARGET",TEXT(Targets!$B$4-$D13,"0.0%")&" to go"))
B14: =IF($A14="","",COUNTIFS('Post Log'!$A$4:$A$203,">="&$A14,'Post Log'!$A$4:$A$203,"<"&$A14+7)) | C14: =IF($A14="","",SUMIFS('Post Log'!$I$4:$I$203,'Post Log'!$A$4:$A$203,">="&$A14,'Post Log'!$A$4:$A$203,"<"&$A14+7)) | D14: =IF(OR($A14="",SUMIFS('Post Log'!$I$4:$I$203,'Post Log'!$A$4:$A$203,">="&$A14,'Post Log'!$A$4:$A$203,"<"&$A14+7)=0),"",SUMIFS('Post Log'!$J$4:$J$203,'Post Log'!$A$4:$A$203,">="&$A14,'Post Log'!$A$4:$A$203,"<"&$A14+7)/SUMIFS('Post Log'!$I$4:$I$203,'Post Log'!$A$4:$A$203,">="&$A14,'Post Log'!$A$4:$A$203,"<"&$A14+7)) | E14: =IF(OR($A14="",SUMIFS('Post Log'!$M$4:$M$203,'Post Log'!$A$4:$A$203,">="&$A14,'Post Log'!$A$4:$A$203,"<"&$A14+7)=0),"",SUMIFS('Post Log'!$L$4:$L$203,'Post Log'!$A$4:$A$203,">="&$A14,'Post Log'!$A$4:$A$203,"<"&$A14+7)/SUMIFS('Post Log'!$M$4:$M$203,'Post Log'!$A$4:$A$203,">="&$A14,'Post Log'!$A$4:$A$203,"<"&$A14+7)) | F14: =IF($A14="","",SUMIFS('Post Log'!$O$4:$O$203,'Post Log'!$A$4:$A$203,">="&$A14,'Post Log'!$A$4:$A$203,"<"&$A14+7)+SUMIFS('Post Log'!$P$4:$P$203,'Post Log'!$A$4:$A$203,">="&$A14,'Post Log'!$A$4:$A$203,"<"&$A14+7)) | G14: =IF($A14="","",SUMIFS('Post Log'!$Q$4:$Q$203,'Post Log'!$A$4:$A$203,">="&$A14,'Post Log'!$A$4:$A$203,"<"&$A14+7)) | H14: =IF($A14="","",SUMIFS('Post Log'!$R$4:$R$203,'Post Log'!$A$4:$A$203,">="&$A14,'Post Log'!$A$4:$A$203,"<"&$A14+7)) | I14: =IF($A14="","",SUMIFS('Post Log'!$S$4:$S$203,'Post Log'!$A$4:$A$203,">="&$A14,'Post Log'!$A$4:$A$203,"<"&$A14+7)) | L14: =IF($D14="","",IF($D14>=Targets!$B$4,"ON TARGET",TEXT(Targets!$B$4-$D14,"0.0%")&" to go"))
B15: =IF($A15="","",COUNTIFS('Post Log'!$A$4:$A$203,">="&$A15,'Post Log'!$A$4:$A$203,"<"&$A15+7)) | C15: =IF($A15="","",SUMIFS('Post Log'!$I$4:$I$203,'Post Log'!$A$4:$A$203,">="&$A15,'Post Log'!$A$4:$A$203,"<"&$A15+7)) | D15: =IF(OR($A15="",SUMIFS('Post Log'!$I$4:$I$203,'Post Log'!$A$4:$A$203,">="&$A15,'Post Log'!$A$4:$A$203,"<"&$A15+7)=0),"",SUMIFS('Post Log'!$J$4:$J$203,'Post Log'!$A$4:$A$203,">="&$A15,'Post Log'!$A$4:$A$203,"<"&$A15+7)/SUMIFS('Post Log'!$I$4:$I$203,'Post Log'!$A$4:$A$203,">="&$A15,'Post Log'!$A$4:$A$203,"<"&$A15+7)) | E15: =IF(OR($A15="",SUMIFS('Post Log'!$M$4:$M$203,'Post Log'!$A$4:$A$203,">="&$A15,'Post Log'!$A$4:$A$203,"<"&$A15+7)=0),"",SUMIFS('Post Log'!$L$4:$L$203,'Post Log'!$A$4:$A$203,">="&$A15,'Post Log'!$A$4:$A$203,"<"&$A15+7)/SUMIFS('Post Log'!$M$4:$M$203,'Post Log'!$A$4:$A$203,">="&$A15,'Post Log'!$A$4:$A$203,"<"&$A15+7)) | F15: =IF($A15="","",SUMIFS('Post Log'!$O$4:$O$203,'Post Log'!$A$4:$A$203,">="&$A15,'Post Log'!$A$4:$A$203,"<"&$A15+7)+SUMIFS('Post Log'!$P$4:$P$203,'Post Log'!$A$4:$A$203,">="&$A15,'Post Log'!$A$4:$A$203,"<"&$A15+7)) | G15: =IF($A15="","",SUMIFS('Post Log'!$Q$4:$Q$203,'Post Log'!$A$4:$A$203,">="&$A15,'Post Log'!$A$4:$A$203,"<"&$A15+7)) | H15: =IF($A15="","",SUMIFS('Post Log'!$R$4:$R$203,'Post Log'!$A$4:$A$203,">="&$A15,'Post Log'!$A$4:$A$203,"<"&$A15+7)) | I15: =IF($A15="","",SUMIFS('Post Log'!$S$4:$S$203,'Post Log'!$A$4:$A$203,">="&$A15,'Post Log'!$A$4:$A$203,"<"&$A15+7)) | L15: =IF($D15="","",IF($D15>=Targets!$B$4,"ON TARGET",TEXT(Targets!$B$4-$D15,"0.0%")&" to go"))
B16: =IF($A16="","",COUNTIFS('Post Log'!$A$4:$A$203,">="&$A16,'Post Log'!$A$4:$A$203,"<"&$A16+7)) | C16: =IF($A16="","",SUMIFS('Post Log'!$I$4:$I$203,'Post Log'!$A$4:$A$203,">="&$A16,'Post Log'!$A$4:$A$203,"<"&$A16+7)) | D16: =IF(OR($A16="",SUMIFS('Post Log'!$I$4:$I$203,'Post Log'!$A$4:$A$203,">="&$A16,'Post Log'!$A$4:$A$203,"<"&$A16+7)=0),"",SUMIFS('Post Log'!$J$4:$J$203,'Post Log'!$A$4:$A$203,">="&$A16,'Post Log'!$A$4:$A$203,"<"&$A16+7)/SUMIFS('Post Log'!$I$4:$I$203,'Post Log'!$A$4:$A$203,">="&$A16,'Post Log'!$A$4:$A$203,"<"&$A16+7)) | E16: =IF(OR($A16="",SUMIFS('Post Log'!$M$4:$M$203,'Post Log'!$A$4:$A$203,">="&$A16,'Post Log'!$A$4:$A$203,"<"&$A16+7)=0),"",SUMIFS('Post Log'!$L$4:$L$203,'Post Log'!$A$4:$A$203,">="&$A16,'Post Log'!$A$4:$A$203,"<"&$A16+7)/SUMIFS('Post Log'!$M$4:$M$203,'Post Log'!$A$4:$A$203,">="&$A16,'Post Log'!$A$4:$A$203,"<"&$A16+7)) | F16: =IF($A16="","",SUMIFS('Post Log'!$O$4:$O$203,'Post Log'!$A$4:$A$203,">="&$A16,'Post Log'!$A$4:$A$203,"<"&$A16+7)+SUMIFS('Post Log'!$P$4:$P$203,'Post Log'!$A$4:$A$203,">="&$A16,'Post Log'!$A$4:$A$203,"<"&$A16+7)) | G16: =IF($A16="","",SUMIFS('Post Log'!$Q$4:$Q$203,'Post Log'!$A$4:$A$203,">="&$A16,'Post Log'!$A$4:$A$203,"<"&$A16+7)) | H16: =IF($A16="","",SUMIFS('Post Log'!$R$4:$R$203,'Post Log'!$A$4:$A$203,">="&$A16,'Post Log'!$A$4:$A$203,"<"&$A16+7)) | I16: =IF($A16="","",SUMIFS('Post Log'!$S$4:$S$203,'Post Log'!$A$4:$A$203,">="&$A16,'Post Log'!$A$4:$A$203,"<"&$A16+7)) | L16: =IF($D16="","",IF($D16>=Targets!$B$4,"ON TARGET",TEXT(Targets!$B$4-$D16,"0.0%")&" to go"))
... B29: =IF($A29="","",COUNTIFS('Post Log'!$A$4:$A$203,">="&$A29,'Post Log'!$A$4:$A$203,"<"&$A29+7)) | C29: =IF($A29="","",SUMIFS('Post Log'!$I$4:$I$203,'Post Log'!$A$4:$A$203,">="&$A29,'Post Log'!$A$4:$A$203,"<"&$A29+7)) | D29: =IF(OR($A29="",SUMIFS('Post Log'!$I$4:$I$203,'Post Log'!$A$4:$A$203,">="&$A29,'Post Log'!$A$4:$A$203,"<"&$A29+7)=0),"",SUMIFS('Post Log'!$J$4:$J$203,'Post Log'!$A$4:$A$203,">="&$A29,'Post Log'!$A$4:$A$203,"<"&$A29+7)/SUMIFS('Post Log'!$I$4:$I$203,'Post Log'!$A$4:$A$203,">="&$A29,'Post Log'!$A$4:$A$203,"<"&$A29+7)) | E29: =IF(OR($A29="",SUMIFS('Post Log'!$M$4:$M$203,'Post Log'!$A$4:$A$203,">="&$A29,'Post Log'!$A$4:$A$203,"<"&$A29+7)=0),"",SUMIFS('Post Log'!$L$4:$L$203,'Post Log'!$A$4:$A$203,">="&$A29,'Post Log'!$A$4:$A$203,"<"&$A29+7)/SUMIFS('Post Log'!$M$4:$M$203,'Post Log'!$A$4:$A$203,">="&$A29,'Post Log'!$A$4:$A$203,"<"&$A29+7)) | F29: =IF($A29="","",SUMIFS('Post Log'!$O$4:$O$203,'Post Log'!$A$4:$A$203,">="&$A29,'Post Log'!$A$4:$A$203,"<"&$A29+7)+SUMIFS('Post Log'!$P$4:$P$203,'Post Log'!$A$4:$A$203,">="&$A29,'Post Log'!$A$4:$A$203,"<"&$A29+7)) | G29: =IF($A29="","",SUMIFS('Post Log'!$Q$4:$Q$203,'Post Log'!$A$4:$A$203,">="&$A29,'Post Log'!$A$4:$A$203,"<"&$A29+7)) | H29: =IF($A29="","",SUMIFS('Post Log'!$R$4:$R$203,'Post Log'!$A$4:$A$203,">="&$A29,'Post Log'!$A$4:$A$203,"<"&$A29+7)) | I29: =IF($A29="","",SUMIFS('Post Log'!$S$4:$S$203,'Post Log'!$A$4:$A$203,">="&$A29,'Post Log'!$A$4:$A$203,"<"&$A29+7)) | L29: =IF($D29="","",IF($D29>=Targets!$B$4,"ON TARGET",TEXT(Targets!$B$4-$D29,"0.0%")&" to go"))

Sheet Leads
A1: LEADS — every DM and WhatsApp conversation, no exceptions
A2: Log on arrival, update at +7 days. The Timing question is what sorts buyers from browsers. Days open flags anything stale: >7 days with no outcome turns red. Malaysian car buyers research for ~2 months, so a 'not yet' is not a no - it is a follow-up date.
A3: Date in | B3: Name | C3: Source post (date) | D3: Channel | E3: Model wanted | F3: Budget / monthly | G3: Timing | H3: Temperature | I3: Dealer routed | J3: Intro made? | K3: Outcome | L3: Follow-up date | M3: Days open | N3: Notes
A4: 46259 | B4: [name] | C4: 2026-08-25 | D4: Messenger | E4: Vellfire 2.5 | F4: RM1,800/bln | G4: Dalam 2 minggu | H4: HOT (<2 weeks) | I4: [dealer name] | J4: Yes | K4: Viewing booked | L4: 46266 | M4: =IF($A4="","",IF($K4<>"","",TODAY()-$A4)) | N4: EXAMPLE ROW - delete before use. 3-way WhatsApp group created.
M5: =IF($A5="","",IF($K5<>"","",TODAY()-$A5))
M6: =IF($A6="","",IF($K6<>"","",TODAY()-$A6))
M7: =IF($A7="","",IF($K7<>"","",TODAY()-$A7))
M8: =IF($A8="","",IF($K8<>"","",TODAY()-$A8))
M9: =IF($A9="","",IF($K9<>"","",TODAY()-$A9))
M10: =IF($A10="","",IF($K10<>"","",TODAY()-$A10))
M11: =IF($A11="","",IF($K11<>"","",TODAY()-$A11))
M12: =IF($A12="","",IF($K12<>"","",TODAY()-$A12))
M13: =IF($A13="","",IF($K13<>"","",TODAY()-$A13))
M14: =IF($A14="","",IF($K14<>"","",TODAY()-$A14))
M15: =IF($A15="","",IF($K15<>"","",TODAY()-$A15))
M16: =IF($A16="","",IF($K16<>"","",TODAY()-$A16))
... M83: =IF($A83="","",IF($K83<>"","",TODAY()-$A83))

Sheet Experiments
A1: EXPERIMENTS — hook A/B tests and the weekly out-of-niche Experiment day
A2: One row per test. A hook style is BANKED into PLAYBOOK.md after it beats 25% twice. An Experiment-day format becomes permanent when it beats the 4-week median of the slot it displaced. Write the hypothesis BEFORE the result - a hypothesis written afterwards is just a description.
A3: Date | B3: Type | C3: What was tested | D3: Hypothesis (written first) | E3: Control / A result | F3: Variant / B result | G3: Winner | H3: Verdict | I3: Ported to PLAYBOOK?
A4: 46259 | B4: Hook A/B | C4: Price shock vs Cold sound open | D4: A cold engine-start with no music holds longer than a price card, because sound-off viewers still see motion | E4: 14% 3-sec | F4: EXAMPLE - delete | G4: B | H4: EXAMPLE ROW - delete before use | I4: Pending

Sheet Targets
A1: TARGETS & BASELINE — the 90-day ladder. Edit here; Weekly reads it.
A2: Baseline is your own recorded data (Jul 21 - Aug 17 2026, 28 days) from urban-auto-hub/WEEKLY-TASK.md. Not an estimate. The Weekly tab's 'North star vs target' column reads cell B4.
A3: Metric | B3: Day 30 target | C3: Day 60 target | D3: Day 90 target | E3: Baseline (Jul21-Aug17) | F3: Note
A4: 3-sec rate ** NORTH STAR ** | B4: 0.2 | C4: 0.25 | D4: 0.3 | E4: 0.14 | F4: Everything else is downstream of this. Healthy is 25-35%.
A5: Posts published / week | B5: 7 | C5: 7 | D5: 7 | E5: 5 | F5: Cadence sits inside the healthy 3-5 feed + 2-4 Reels band.
A6: Outbound comments / week | B6: 50 | C6: 75 | D6: 75 | E6: 0 | F6: The only INPUT metric here - the one you fully control.
A7: Comments received / month | B7: 20 | C7: 40 | D7: 60 | E7: 4 | F7: Lower the answer cost: one word or one letter.
A8: Saves + shares / month | B8: track | C8: 40 | D8: 80 | E8: not tracked | F8: Strongest Reels ranking signals.
A9: Net follows / month | B9: 50 | C9: 150 | D9: 300 | E9: -15 | F9: Baseline was NEGATIVE - zero acquisition, not churn.
A10: WhatsApp convos / month | B10: 6 | C10: 12 | D10: 20 | E10: 2 | F10: The money metric. Fix the CTA friction first.
A11: Active dealer partners | B11: 2 | C11: 3 | D11: 4 | E11: ? | F11: Approach with a free sample, then quote.
A14: DECISION RULES
A15: SCALE a format | B15: 3-sec >= 25% on 3 consecutive runs -> +1 slot per week
A16: KILL a format | B16: 3-sec < 15% on 3 consecutive runs -> drop it, reassign the slot
A17: BANK a hook style | B17: >= 25% twice -> PLAYBOOK.md 'Patterns added'
A18: REPOST with hook B | B18: 3-sec < 20% at 24h -> delete, repost with version B at the next slot
A19: An EXPERIMENT wins | B19: beats the 4-week median of the slot it displaced -> becomes permanent
A20: BOOST a post | B20: only after 48h organic AND 3-sec >= 30% AND >= 1 convo. Never a loser.
A21: DROP a dealer | B21: 3 months, zero enquiries routed, and no document access
A22: REWRITE the strategy | B22: 4 consecutive weeks with no movement on the north star
